django_postgres_hot_upgrade/__init__.py
django_postgres_hot_upgrade/app.py
django_postgres_hot_upgrade-1.1.0.dist-info/LICENSE
django_postgres_hot_upgrade-1.1.0.dist-info/METADATA
django_postgres_hot_upgrade-1.1.0.dist-info/WHEEL
django_postgres_hot_upgrade-1.1.0.dist-info/top_level.txt
django_postgres_hot_upgrade-1.1.0.dist-info/zip-safe
django_postgres_hot_upgrade-1.1.0.dist-info/RECORD
