Metadata-Version: 2.1
Name: django-postgres-hot-upgrade
Version: 1.1.0
Summary: Django app that resets django.contrib.postgres caches that store postgres extensions OIDs
Home-page: https://github.com/peopledoc/django-postgres-hot-upgrade
Author: PeopleDoc
Author-email: mickael.guerin@people-doc.com
License: MIT License
Keywords: django migrations postgresql
Platform: UNKNOWN
Classifier: Development Status :: 4 - Beta
Classifier: Intended Audience :: Developers
Classifier: Programming Language :: Python :: 3
Classifier: Programming Language :: Python :: 3.6
Classifier: Programming Language :: Python :: 3.7
Classifier: Programming Language :: Python :: 3.8
Classifier: License :: OSI Approved :: MIT License
Requires-Dist: Django (>=2.2.0)
Provides-Extra: dev
Requires-Dist: black ; extra == 'dev'
Requires-Dist: check-manifest ; extra == 'dev'
Requires-Dist: flake8 ; extra == 'dev'
Requires-Dist: isort (>=5) ; extra == 'dev'
Requires-Dist: psycopg2-binary ; extra == 'dev'
Requires-Dist: pytest ; extra == 'dev'
Requires-Dist: pytest-django ; extra == 'dev'
Requires-Dist: pytest-mock ; extra == 'dev'
Requires-Dist: tox ; extra == 'dev'
